prometheus/__init__.py
prometheus/backtest.py
prometheus/callback.py
prometheus/kline.py
prometheus/strategy.py
prometheus/technical_analysis.py
prometheus/base/__init__.py
prometheus/base/asynchronous.py
prometheus/base/protocol.py
prometheus/base/synchronous.py
prometheus_quant-1.1.2.dist-info/METADATA
prometheus_quant-1.1.2.dist-info/WHEEL
prometheus_quant-1.1.2.dist-info/top_level.txt
prometheus_quant-1.1.2.dist-info/RECORD
