Metadata-Version: 2.1
Name: prometheus-quant
Version: 1.1.2
Summary: Python Study and API of Prometheus Quant Trade System.
Home-page: UNKNOWN
Author: Eddy Xie
Author-email: xieshufan@163.com
License: MIT
Keywords: python,quant,quantitative,ctp,trading,future
Platform: UNKNOWN
Classifier: Development Status :: 5 - Production/Stable
Classifier: Operating System :: OS Independent
Classifier: Programming Language :: Python :: 3
Classifier: Programming Language :: Python :: 3.5
Classifier: Programming Language :: Python :: 3.6
Classifier: Programming Language :: Python :: 3.7
Classifier: Programming Language :: Python :: 3.8
Classifier: Programming Language :: Python :: 3.9
Classifier: Programming Language :: Python :: 3.10
Classifier: Topic :: Office/Business :: Financial :: Investment
Classifier: Programming Language :: Python :: Implementation :: CPython
Classifier: License :: OSI Approved :: MIT License
Classifier: Natural Language :: Chinese (Simplified)
Requires-Dist: plotly
Requires-Dist: dash
Requires-Dist: numpy
Requires-Dist: pymysql
Requires-Dist: sqlalchemy
Requires-Dist: pandas
Requires-Dist: pyzmq
Requires-Dist: tqdm
